{
  "bpm": 138,
  "tracks": [
    {
      "id": "7aaf9262",
      "name": "Kick",
      "steps": [
        true,
        false,
        false,
        true,
        false,
        true,
        false,
        true,
        true,
        false,
        false,
        true,
        false,
        true,
        false,
        true
      ],
      "volume": 0.8,
      "mute": false,
      "color": "#e74c3c"
    },
    {
      "id": "ff715a40",
      "name": "Snare",
      "steps": [
        false,
        true,
        false,
        false,
        false,
        false,
        true,
        false,
        false,
        false,
        false,
        true,
        false,
        false,
        true,
        false
      ],
      "volume": 0.8,
      "mute": false,
      "color": "#3498db"
    },
    {
      "id": "e715f9d7",
      "name": "Hi-Hat",
      "steps": [
        true,
        true,
        true,
        false,
        true,
        true,
        false,
        false,
        true,
        true,
        true,
        false,
        true,
        true,
        false,
        false
      ],
      "volume": 0.8,
      "mute": false,
      "color": "#2ecc71"
    },
    {
      "id": "c44b1fd4",
      "name": "Clap",
      "steps": [
        false,
        false,
        false,
        false,
        true,
        false,
        false,
        false,
        false,
        false,
        false,
        false,
        false,
        true,
        false,
        false
      ],
      "volume": 0.8,
      "mute": false,
      "color": "#e67e22"
    },
    {
      "id": "31745908",
      "name": "Hi Tom",
      "steps": [
        false,
        false,
        false,
        false,
        false,
        false,
        false,
        false,
        false,
        false,
        true,
        false,
        false,
        false,
        false,
        false
      ],
      "volume": 0.8,
      "mute": false,
      "color": "#9b59b6"
    },
    {
      "id": "ec4f85d7",
      "name": "Mid Tom",
      "steps": [
        false,
        false,
        false,
        false,
        false,
        false,
        false,
        false,
        false,
        false,
        false,
        false,
        false,
        false,
        false,
        false
      ],
      "volume": 0.8,
      "mute": false,
      "color": "#1abc9c"
    },
    {
      "id": "65ffa17a",
      "name": "Floor Tom",
      "steps": [
        false,
        false,
        false,
        false,
        false,
        false,
        false,
        false,
        false,
        false,
        false,
        false,
        false,
        false,
        false,
        false
      ],
      "volume": 0.8,
      "mute": false,
      "color": "#e91e63"
    },
    {
      "id": "0d42a003",
      "name": "Ride",
      "steps": [
        false,
        false,
        false,
        false,
        false,
        false,
        false,
        false,
        false,
        false,
        false,
        false,
        false,
        false,
        false,
        false
      ],
      "volume": 0.8,
      "mute": false,
      "color": "#f39c12"
    },
    {
      "id": "96f7d2d5",
      "name": "Crash",
      "steps": [
        false,
        false,
        false,
        false,
        false,
        false,
        false,
        false,
        false,
        false,
        false,
        false,
        false,
        false,
        false,
        false
      ],
      "volume": 0.8,
      "mute": false,
      "color": "#16a085"
    },
    {
      "id": "9fba18ca",
      "name": "Cowbell",
      "steps": [
        false,
        false,
        false,
        false,
        false,
        false,
        false,
        false,
        false,
        false,
        false,
        false,
        false,
        false,
        false,
        false
      ],
      "volume": 0.8,
      "mute": false,
      "color": "#c0392b"
    }
  ]
}